{
  "configVersion": 1,
  "timestamp": 1676327777586,
  "index": "/battle-scribe-tools/index.html",
  "assetGroups": [
    {
      "name": "app",
      "installMode": "prefetch",
      "updateMode": "prefetch",
      "cacheQueryOptions": {
        "ignoreVary": true
      },
      "urls": [
        "/battle-scribe-tools/1033.6de0b6c3cefc2941.js",
        "/battle-scribe-tools/1118.caec897d75bac315.js",
        "/battle-scribe-tools/1186.2146decda833510c.js",
        "/battle-scribe-tools/1217.81c6c1e3c33f8d34.js",
        "/battle-scribe-tools/1435.19a71942a06e3082.js",
        "/battle-scribe-tools/1536.d3fc7bf985737c36.js",
        "/battle-scribe-tools/1650.7988cbea3c4ebf0c.js",
        "/battle-scribe-tools/1709.f6a0887907f381c8.js",
        "/battle-scribe-tools/205.b15471b053883f89.js",
        "/battle-scribe-tools/2073.013249fefd2069d3.js",
        "/battle-scribe-tools/2175.84d55e14c61280c9.js",
        "/battle-scribe-tools/2289.28fdfa207a29c3cc.js",
        "/battle-scribe-tools/2349.203e71d173a9e5a9.js",
        "/battle-scribe-tools/2531.31ce3b7982271de4.js",
        "/battle-scribe-tools/2698.e950bf7ce9ebb461.js",
        "/battle-scribe-tools/2773.625e41ac29599320.js",
        "/battle-scribe-tools/3236.e85f91e242fbfc27.js",
        "/battle-scribe-tools/3446.5bc18f0301303980.js",
        "/battle-scribe-tools/3648.d7ad91f74ce607fd.js",
        "/battle-scribe-tools/3804.788376ecf660fc9d.js",
        "/battle-scribe-tools/388.245d97b43279e7c9.js",
        "/battle-scribe-tools/3923.ed5ef35c7a3ea874.js",
        "/battle-scribe-tools/4174.75d953f03422bb14.js",
        "/battle-scribe-tools/4276.25104c4ebdc23311.js",
        "/battle-scribe-tools/4330.aa631cc28de944d6.js",
        "/battle-scribe-tools/4376.f2371e956bffc131.js",
        "/battle-scribe-tools/438.bb9390ee4ac1e376.js",
        "/battle-scribe-tools/4432.b2d4f138c79499ed.js",
        "/battle-scribe-tools/4651.e8c233ba2a851d56.js",
        "/battle-scribe-tools/4711.bc06e8e2ed8d466e.js",
        "/battle-scribe-tools/4753.a29d276a3a205d81.js",
        "/battle-scribe-tools/4908.e086aa630a0d0457.js",
        "/battle-scribe-tools/4959.0a385a433998bfa9.js",
        "/battle-scribe-tools/5168.05306a2ed1f19fde.js",
        "/battle-scribe-tools/5227.b37088d2e6f6161e.js",
        "/battle-scribe-tools/5349.5189feab479a9ebb.js",
        "/battle-scribe-tools/5652.93b64d12e662cc3e.js",
        "/battle-scribe-tools/5817.97c1e03a1729ac95.js",
        "/battle-scribe-tools/5836.e6faeb9b0839f841.js",
        "/battle-scribe-tools/6120.61c7c0af749de030.js",
        "/battle-scribe-tools/6183.e8cc497001abb54a.js",
        "/battle-scribe-tools/6560.0d4e3cd9b3c68e7d.js",
        "/battle-scribe-tools/657.1b2cf675051045e1.js",
        "/battle-scribe-tools/7030.7483427069ade91b.js",
        "/battle-scribe-tools/7544.17c47bd18a7f0257.js",
        "/battle-scribe-tools/7602.3b1f7bbe1e17e9bc.js",
        "/battle-scribe-tools/8136.fc81ec41b3140b1c.js",
        "/battle-scribe-tools/8221.7eb1fc8533d7077b.js",
        "/battle-scribe-tools/8628.d6c83f27f8dc5834.js",
        "/battle-scribe-tools/8939.8ec1260fc842fb07.js",
        "/battle-scribe-tools/9016.8202abe25ac1d990.js",
        "/battle-scribe-tools/9230.eef8846bed09a430.js",
        "/battle-scribe-tools/9325.df2eafa84566460f.js",
        "/battle-scribe-tools/9434.0859771623af50d1.js",
        "/battle-scribe-tools/9536.4cd4484d6edfb3f0.js",
        "/battle-scribe-tools/9652.66f65c5a55eb098c.js",
        "/battle-scribe-tools/9654.c617cb0e88598647.js",
        "/battle-scribe-tools/9824.09d020f17491b308.js",
        "/battle-scribe-tools/9922.fa46f0ec88b4781f.js",
        "/battle-scribe-tools/9958.5ca539341099a652.js",
        "/battle-scribe-tools/common.4c46724c555e2737.js",
        "/battle-scribe-tools/favicon.ico",
        "/battle-scribe-tools/index.html",
        "/battle-scribe-tools/main.23fcae842cd70cfa.js",
        "/battle-scribe-tools/manifest.webmanifest",
        "/battle-scribe-tools/polyfills-core-js.be3c4db4ba12d4e4.js",
        "/battle-scribe-tools/polyfills-dom.55a512cb243f4299.js",
        "/battle-scribe-tools/polyfills.7e22781db45a7d3e.js",
        "/battle-scribe-tools/runtime.0192887abd891464.js",
        "/battle-scribe-tools/styles.ad414dd5193f8dda.css"
      ],
      "patterns": []
    },
    {
      "name": "assets",
      "installMode": "lazy",
      "updateMode": "prefetch",
      "cacheQueryOptions": {
        "ignoreVary": true
      },
      "urls": [
        "/battle-scribe-tools/assets/icons/icon-128x128.png",
        "/battle-scribe-tools/assets/icons/icon-144x144.png",
        "/battle-scribe-tools/assets/icons/icon-152x152.png",
        "/battle-scribe-tools/assets/icons/icon-192x192.png",
        "/battle-scribe-tools/assets/icons/icon-384x384.png",
        "/battle-scribe-tools/assets/icons/icon-512x512.png",
        "/battle-scribe-tools/assets/icons/icon-72x72.png",
        "/battle-scribe-tools/assets/icons/icon-96x96.png"
      ],
      "patterns": []
    }
  ],
  "dataGroups": [],
  "hashTable": {
    "/battle-scribe-tools/1033.6de0b6c3cefc2941.js": "e3926e8969d8ccac78b387fdcb5ca3e56c914504",
    "/battle-scribe-tools/1118.caec897d75bac315.js": "97033a5318e7eb40b623f81bc728f09a222e05ee",
    "/battle-scribe-tools/1186.2146decda833510c.js": "dcc576b04660de9c08d90593adc99405a281db0c",
    "/battle-scribe-tools/1217.81c6c1e3c33f8d34.js": "372765d4754f261e9de2e5297504c9b2f1807b28",
    "/battle-scribe-tools/1435.19a71942a06e3082.js": "89d6714ea02f20fd8d01d5646c163ee9c06b9235",
    "/battle-scribe-tools/1536.d3fc7bf985737c36.js": "457a2ab1f2a3e69cc84a14d8f6fa7230a81838d2",
    "/battle-scribe-tools/1650.7988cbea3c4ebf0c.js": "66c551e92b71085ecd50bfeb3819dd843bee0864",
    "/battle-scribe-tools/1709.f6a0887907f381c8.js": "fb04b4be8583ae2e7d0c66cd99a702481761d68d",
    "/battle-scribe-tools/205.b15471b053883f89.js": "43fd7faa1b412b0436c362084ed6f9a74e789f10",
    "/battle-scribe-tools/2073.013249fefd2069d3.js": "e2bc9e89759b666dfee11c4d719d8cdd9acda8bc",
    "/battle-scribe-tools/2175.84d55e14c61280c9.js": "06944591ab17526380c3df74d2456607c7f19183",
    "/battle-scribe-tools/2289.28fdfa207a29c3cc.js": "1d95d28c7fbb5fd5adc2a8d85cfbec4149a6ad18",
    "/battle-scribe-tools/2349.203e71d173a9e5a9.js": "40924dfce0ac20b12b1ecb3fa239415811a63e80",
    "/battle-scribe-tools/2531.31ce3b7982271de4.js": "c54131287699c5a132ecd592c0d98c84328d3fdd",
    "/battle-scribe-tools/2698.e950bf7ce9ebb461.js": "97eace0a8ac520294392fcf452a101a06d85ca30",
    "/battle-scribe-tools/2773.625e41ac29599320.js": "b96cbd90fa01c35ce957b0a9deb1b329d289a5bc",
    "/battle-scribe-tools/3236.e85f91e242fbfc27.js": "1f87626e91f77183dc7db87f369c5a9ca8cced25",
    "/battle-scribe-tools/3446.5bc18f0301303980.js": "14db4c75979fe2219f67f3cfbd050c4005aeac9b",
    "/battle-scribe-tools/3648.d7ad91f74ce607fd.js": "87caf684b87d593ea922cbb03612094749896b66",
    "/battle-scribe-tools/3804.788376ecf660fc9d.js": "e902f7846e44c98fe58034bd6b4ba3048803bb0f",
    "/battle-scribe-tools/388.245d97b43279e7c9.js": "06bbe9637128ce32ae62b1f2fee78fd61e97be63",
    "/battle-scribe-tools/3923.ed5ef35c7a3ea874.js": "9ef3483091eb6337f29ee31fae3997f7f6d3915b",
    "/battle-scribe-tools/4174.75d953f03422bb14.js": "c157e13f7ab1b2b9ec76a70c2ae13d7c5a64dc11",
    "/battle-scribe-tools/4276.25104c4ebdc23311.js": "e988d16775391655b4f917b26676ba97ff92df6d",
    "/battle-scribe-tools/4330.aa631cc28de944d6.js": "d6b5b2b0a11ee924e8892121c07a61a28e123e00",
    "/battle-scribe-tools/4376.f2371e956bffc131.js": "eff48bc8c9fd8df31782ba497a59f31928be7720",
    "/battle-scribe-tools/438.bb9390ee4ac1e376.js": "0a881809a1445ba0fb218ce0c1c226a2fe1a72bd",
    "/battle-scribe-tools/4432.b2d4f138c79499ed.js": "853a53a34b66c17f433c8ec8a2c724773d152066",
    "/battle-scribe-tools/4651.e8c233ba2a851d56.js": "c1fb3f218c2a6955a0e55ac3047f2dc8c5399b1f",
    "/battle-scribe-tools/4711.bc06e8e2ed8d466e.js": "74b68fd34615f69aab37f31d1e41fce90e7e1b86",
    "/battle-scribe-tools/4753.a29d276a3a205d81.js": "9b4b18db2b52c02e50e4c8b811ba8af9f042e43d",
    "/battle-scribe-tools/4908.e086aa630a0d0457.js": "52cfcf8a436736c6dea16825e5400ed3f8d43110",
    "/battle-scribe-tools/4959.0a385a433998bfa9.js": "3ef1fbb7bf8e481864ffac8c7858d7b0c836598e",
    "/battle-scribe-tools/5168.05306a2ed1f19fde.js": "9441afa5703c7a5eafe9fca9b421872ee189b21d",
    "/battle-scribe-tools/5227.b37088d2e6f6161e.js": "301a35209a34407e690dc6681b0d84cbbcbe8bf2",
    "/battle-scribe-tools/5349.5189feab479a9ebb.js": "40dbc7bda8fa524b39fbae2281faf18db251d342",
    "/battle-scribe-tools/5652.93b64d12e662cc3e.js": "9eaf18ff33baac8f71681c8efc86096e29a9bfbb",
    "/battle-scribe-tools/5817.97c1e03a1729ac95.js": "1b68e3b3b331dbf97df61efa77af76e1e707c453",
    "/battle-scribe-tools/5836.e6faeb9b0839f841.js": "039b0137f1d2f4ba77d4477863bb4d5b2ab4cce5",
    "/battle-scribe-tools/6120.61c7c0af749de030.js": "e7f2e9f2e4b458f7ce1d7f7b8f2a5634969323bc",
    "/battle-scribe-tools/6183.e8cc497001abb54a.js": "0f3652375d2f9f036bc1d75b70ac55bd0c5a131b",
    "/battle-scribe-tools/6560.0d4e3cd9b3c68e7d.js": "f1a9ae5ccdbda8a7e60998c8724ce5c684d9b313",
    "/battle-scribe-tools/657.1b2cf675051045e1.js": "b7f96ae3e18febfbeabafc66e8133ec4b0fb072b",
    "/battle-scribe-tools/7030.7483427069ade91b.js": "d27a91f32dbf40a9dccb2f0c544ea19468abb44e",
    "/battle-scribe-tools/7544.17c47bd18a7f0257.js": "fdd21710949de0b474d87179b47cb8554f35779b",
    "/battle-scribe-tools/7602.3b1f7bbe1e17e9bc.js": "3dd443a82359cef4d936783f83804e2fa845b9a8",
    "/battle-scribe-tools/8136.fc81ec41b3140b1c.js": "c421367a6036d1341b7db2f580b94562849d1f46",
    "/battle-scribe-tools/8221.7eb1fc8533d7077b.js": "b36991d74e8291eec7adc2032009bbd5e6258e7b",
    "/battle-scribe-tools/8628.d6c83f27f8dc5834.js": "e9c3e25df5bc651b11ec05cbfc20d6886e490a0a",
    "/battle-scribe-tools/8939.8ec1260fc842fb07.js": "99f909f9fd9ed981a5543cbb23f8bcda1e2e2c5c",
    "/battle-scribe-tools/9016.8202abe25ac1d990.js": "ab2cc2c94ab77d6702528b62790b9970d2337a9a",
    "/battle-scribe-tools/9230.eef8846bed09a430.js": "23746e46d29f6aa25cbba5e0eeb7e82b8774c956",
    "/battle-scribe-tools/9325.df2eafa84566460f.js": "1b3b5f8c79bd00e4adc1e7ea333392bdae96ce3a",
    "/battle-scribe-tools/9434.0859771623af50d1.js": "471f94fbbcfc306a6ab88e6c37b9693ec61c18c9",
    "/battle-scribe-tools/9536.4cd4484d6edfb3f0.js": "e06f111f9271f45957ebac0ad6e1df1395f4f338",
    "/battle-scribe-tools/9652.66f65c5a55eb098c.js": "62acf7cc76c64f7adc0390a5582632319dcd5a6d",
    "/battle-scribe-tools/9654.c617cb0e88598647.js": "aa79b5c9552c707feea05adfce87f9798f536244",
    "/battle-scribe-tools/9824.09d020f17491b308.js": "39839226e98b28391baaaf5b80cd55fdfbdc86c9",
    "/battle-scribe-tools/9922.fa46f0ec88b4781f.js": "a6beb0a8b2c0697d5a42ef732233b2e214b5068d",
    "/battle-scribe-tools/9958.5ca539341099a652.js": "f91085439c15590b782bdecfd0a07cefe5bec1fd",
    "/battle-scribe-tools/assets/icons/icon-128x128.png": "dae3b6ed49bdaf4327b92531d4b5b4a5d30c7532",
    "/battle-scribe-tools/assets/icons/icon-144x144.png": "b0bd89982e08f9bd2b642928f5391915b74799a7",
    "/battle-scribe-tools/assets/icons/icon-152x152.png": "7479a9477815dfd9668d60f8b3b2fba709b91310",
    "/battle-scribe-tools/assets/icons/icon-192x192.png": "1abd80d431a237a853ce38147d8c63752f10933b",
    "/battle-scribe-tools/assets/icons/icon-384x384.png": "329749cd6393768d3131ed6304c136b1ca05f2fd",
    "/battle-scribe-tools/assets/icons/icon-512x512.png": "559d9c4318b45a1f2b10596bbb4c960fe521dbcc",
    "/battle-scribe-tools/assets/icons/icon-72x72.png": "c457e56089a36952cd67156f9996bc4ce54a5ed9",
    "/battle-scribe-tools/assets/icons/icon-96x96.png": "3914125a4b445bf111c5627875fc190f560daa41",
    "/battle-scribe-tools/common.4c46724c555e2737.js": "fabe9fbc79641ead00b8d89e209395f419669ad8",
    "/battle-scribe-tools/favicon.ico": "4e23d0f9b6ddaf3c9ddef90dbaed2342941297b5",
    "/battle-scribe-tools/index.html": "74c06a665c0ff27d539db12f5772bcfdda8b1448",
    "/battle-scribe-tools/main.23fcae842cd70cfa.js": "1fad5a06827e6466a858556564af7f00aed6a943",
    "/battle-scribe-tools/manifest.webmanifest": "54e3778b6e47274d500f5bbf5dba5eeeaf8803dd",
    "/battle-scribe-tools/polyfills-core-js.be3c4db4ba12d4e4.js": "83ec711f891793fe224ec13df63736c3c4734519",
    "/battle-scribe-tools/polyfills-dom.55a512cb243f4299.js": "90ba5cea322637e1d67a9d2dfda588b6c8f51bff",
    "/battle-scribe-tools/polyfills.7e22781db45a7d3e.js": "4856bbbea76ffeb2b50294441da9ecf44dd8c483",
    "/battle-scribe-tools/runtime.0192887abd891464.js": "d496a8603cc63ac9e9e3b859882be274626823b5",
    "/battle-scribe-tools/styles.ad414dd5193f8dda.css": "5c83c0432cc03c87aed9aaafe1423039a28e158e"
  },
  "navigationUrls": [
    {
      "positive": true,
      "regex": "^\\/.*$"
    },
    {
      "positive": false,
      "regex": "^\\/(?:.+\\/)?[^/]*\\.[^/]*$"
    },
    {
      "positive": false,
      "regex": "^\\/(?:.+\\/)?[^/]*__[^/]*$"
    },
    {
      "positive": false,
      "regex": "^\\/(?:.+\\/)?[^/]*__[^/]*\\/.*$"
    }
  ],
  "navigationRequestStrategy": "performance"
}